optigasflow/NGP.py
optigasflow/__init__.py
optigasflow-0.0.3.dist-info/LICENSE
optigasflow-0.0.3.dist-info/METADATA
optigasflow-0.0.3.dist-info/WHEEL
optigasflow-0.0.3.dist-info/top_level.txt
optigasflow-0.0.3.dist-info/RECORD
