Metadata-Version: 2.1
Name: optigasflow
Version: 0.0.3
Summary: A small example package
Author-email: cblancom <cristian.blanco@utp.edu.com>
Project-URL: Homepage, https://github.com/cblancom/natural_gas_project
Classifier: Programming Language :: Python :: 3
Classifier: License :: OSI Approved :: MIT License
Classifier: Operating System :: OS Independent
Requires-Python: >=3.7
License-File: LICENSE
Requires-Dist: cycler
Requires-Dist: et-xmlfile
Requires-Dist: fonttools
Requires-Dist: gekko
Requires-Dist: kiwisolver
Requires-Dist: matplotlib
Requires-Dist: networkx
Requires-Dist: numpy
Requires-Dist: openpyxl
Requires-Dist: packaging
Requires-Dist: pandas
Requires-Dist: Pillow
Requires-Dist: pyparsing
Requires-Dist: python-dateutil
Requires-Dist: pytz
Requires-Dist: scipy
Requires-Dist: six
